aws_cognito/__init__.py
aws_cognito/client.py
myb_aws_cognito_api-1.0.1.dist-info/LICENSE
myb_aws_cognito_api-1.0.1.dist-info/METADATA
myb_aws_cognito_api-1.0.1.dist-info/WHEEL
myb_aws_cognito_api-1.0.1.dist-info/top_level.txt
myb_aws_cognito_api-1.0.1.dist-info/RECORD
