Metadata-Version: 2.1
Name: myb-aws-cognito-api
Version: 1.0.1
Summary: Python library for communicating with the AWS Cognito API
Home-page: https://github.com/mine-your-business/myb-aws-cognito-api
Author: Mine Your Business
Author-email: mine.your.business.crypto@gmail.com
License: GPL-3
Platform: UNKNOWN
Classifier: Programming Language :: Python :: 3
Classifier: License :: OSI Approved :: GNU General Public License v3 (GPLv3)
Classifier: Operating System :: OS Independent
Requires-Python: >=3.7
Requires-Dist: boto3 (==1.17.2)
Requires-Dist: requests (==2.22.0)
